quark/__init__.py
quark/cli.py
quark/config.py
quark/freshquark.py
quark/logo.py
quark/radiocontrast.py
quark/report.py
quark/rulegeneration.py
quark/agent/__init__.py
quark/agent/agentTools.py
quark/agent/prompts.py
quark/agent/quarkAgent.py
quark/agent/quarkAgentWeb.py
quark/core/__init__.py
quark/core/analysis.py
quark/core/apkinfo.py
quark/core/parallelquark.py
quark/core/quark.py
quark/core/r2apkinfo.py
quark/core/rzapkinfo.py
quark/core/shurikenapkinfo.py
quark/core/axmlreader/__init__.py
quark/core/axmlreader/python.py
quark/core/axmlreader/radare2/__init__.py
quark/core/axmlreader/rizin/__init__.py
quark/core/interface/__init__.py
quark/core/interface/baseapkinfo.py
quark/core/struct/__init__.py
quark/core/struct/bytecodeobject.py
quark/core/struct/methodobject.py
quark/core/struct/registerobject.py
quark/core/struct/ruleobject.py
quark/core/struct/tableobject.py
quark/evaluator/__init__.py
quark/evaluator/pyeval.py
quark/forensic/__init__.py
quark/forensic/forensic.py
quark/forensic/vt_analysis.py
quark/script/__init__.py
quark/script/ares.py
quark/script/objection.py
quark/script/utils.py
quark/script/frida/__init__.py
quark/script/frida/agent.js
quark/utils/__init__.py
quark/utils/colors.py
quark/utils/graph.py
quark/utils/output.py
quark/utils/pprint.py
quark/utils/regex.py
quark/utils/tools.py
quark/utils/weight.py
quark/webreport/__init__.py
quark/webreport/analysis_report_layout.html
quark/webreport/generate.py
quark/webreport/genrule_report_layout.html
quark_engine-26.1.1.dist-info/licenses/LICENSE
quark_engine-26.1.1.dist-info/METADATA
quark_engine-26.1.1.dist-info/WHEEL
quark_engine-26.1.1.dist-info/entry_points.txt
quark_engine-26.1.1.dist-info/top_level.txt
quark_engine-26.1.1.dist-info/RECORD
