Metadata-Version: 2.4
Name: quark-engine
Version: 26.1.1
Summary: An Obfuscation-Neglect Android Malware Scoring System
Home-page: https://github.com/quark-engine/quark-engine
Author: YuShiang Dang, ShengFeng Lu, KunYu Chen
Author-email: pulorsok@gmail.com
Classifier: Programming Language :: Python :: 3
Classifier: License :: OSI Approved :: GNU General Public License v3 (GPLv3)
Classifier: Operating System :: OS Independent
Classifier: Topic :: Security
Requires-Python: >=3.10
License-File: LICENSE
Requires-Dist: prettytable>=1.0.0
Requires-Dist: androguard==3.4.0a1
Requires-Dist: tqdm
Requires-Dist: colorama
Requires-Dist: graphviz
Requires-Dist: prompt-toolkit
Requires-Dist: plotly
Requires-Dist: rzpipe
Requires-Dist: click
Requires-Dist: r2pipe==1.8.0
Requires-Dist: pathvalidate==3.2.3
Provides-Extra: quarkagent
Requires-Dist: langchain==0.2.11; extra == "quarkagent"
Requires-Dist: langchain-core==0.2.23; extra == "quarkagent"
Requires-Dist: langchain-openai==0.1.17; extra == "quarkagent"
Requires-Dist: flask==2.2.5; extra == "quarkagent"
Dynamic: author
Dynamic: author-email
Dynamic: classifier
Dynamic: description
Dynamic: description-content-type
Dynamic: home-page
Dynamic: license-file
Dynamic: provides-extra
Dynamic: requires-dist
Dynamic: requires-python
Dynamic: summary
